CHANGES
LICENSE
MANIFEST.in
README
ez_setup.py
setup.py
uWeb.egg-info/PKG-INFO
uWeb.egg-info/SOURCES.txt
uWeb.egg-info/dependency_links.txt
uWeb.egg-info/requires.txt
uWeb.egg-info/top_level.txt
uweb/__init__.py
uweb/model.py
uweb/readme.txt
uweb/request.py
uweb/response.py
uweb/standalone.py
uweb/templateparser.py
uweb/test_model.py
uweb/test_request.py
uweb/test_templateparser.py
uweb/base_project/__init__.py
uweb/base_project/base.conf
uweb/base_project/pages.py
uweb/base_project/readme.txt
uweb/base_project/router/__init__.py
uweb/base_project/router/router.py
uweb/base_project/templates/404.utp
uweb/base_project/templates/index.utp
uweb/ext_lib/underdark/__init__.py
uweb/ext_lib/underdark/libs/__init__.py
uweb/ext_lib/underdark/libs/app/__init__.py
uweb/ext_lib/underdark/libs/app/daemon/__init__.py
uweb/ext_lib/underdark/libs/app/daemon/daemon.py
uweb/ext_lib/underdark/libs/app/daemon/pidlockfile.py
uweb/ext_lib/underdark/libs/app/daemon/runner.py
uweb/ext_lib/underdark/libs/app/daemon/version/__init__.py
uweb/ext_lib/underdark/libs/app/daemon/version/version_info.py
uweb/ext_lib/underdark/libs/app/logging/__init__.py
uweb/ext_lib/underdark/libs/app/logging/config.py
uweb/ext_lib/underdark/libs/app/logging/extras.py
uweb/ext_lib/underdark/libs/app/logging/handlers.py
uweb/ext_lib/underdark/libs/sqltalk/__init__.py
uweb/ext_lib/underdark/libs/sqltalk/sqlresult.py
uweb/ext_lib/underdark/libs/sqltalk/sqlresult_test.py
uweb/ext_lib/underdark/libs/sqltalk/mysql/__init__.py
uweb/ext_lib/underdark/libs/sqltalk/mysql/connection.py
uweb/ext_lib/underdark/libs/sqltalk/mysql/constants.py
uweb/ext_lib/underdark/libs/sqltalk/mysql/converters.py
uweb/ext_lib/underdark/libs/sqltalk/mysql/cursor.py
uweb/ext_lib/underdark/libs/sqltalk/mysql/times.py
uweb/ext_lib/underdark/libs/sqltalk/sqlite/__init__.py
uweb/ext_lib/underdark/libs/sqltalk/sqlite/connection.py
uweb/ext_lib/underdark/libs/sqltalk/sqlite/converters.py
uweb/ext_lib/underdark/libs/sqltalk/sqlite/cursor.py
uweb/logviewer/__init__.py
uweb/logviewer/apache.conf
uweb/logviewer/logging.conf
uweb/logviewer/model.py
uweb/logviewer/viewer.py
