Metadata-Version: 1.1
Name: uWeb
Version: 0.2.9
Summary: Underdark's minimal Web-framework.
Home-page: http://uweb-framework.nl/
Author: Elmer de Looff
Author-email: elmer@underdark.nl
License: ISC
Keywords: web,framework,underdark
Platform: UNKNOWN
Classifier: Development Status :: 3 - Alpha
Classifier: Intended Audience :: Developers
Classifier: License :: OSI Approved :: ISC License (ISCL)
Classifier: Operating System :: MacOS :: MacOS X
Classifier: Operating System :: POSIX :: Linux
